sqliteinterface
